MANIFEST.in
README.md
setup.py
src/histogramy/__init__.py
src/histogramy/demo.py
src/histogramy/describer.py
src/histogramy/loader.py
src/histogramy/main.py
src/histogramy/modulator.py
src/histogramy/options.py
src/histogramy/plotter.py
src/histogramy/prefix.py
src/histogramy/simulator.py
src/histogramy/utils.py
src/histogramy.egg-info/PKG-INFO
src/histogramy.egg-info/SOURCES.txt
src/histogramy.egg-info/dependency_links.txt
src/histogramy.egg-info/entry_points.txt
src/histogramy.egg-info/requires.txt
src/histogramy.egg-info/top_level.txt
src/histogramy.egg-info/zip-safe
static/screenshot.png