Metadata-Version: 1.1
Name: histogramy
Version: 0.1.4
Summary: A small program to analysis 1 dimensional data
Home-page: https://github.com/lambdalisue/histogramy
Author: Alisue
Author-email: lambdalisue@hashnote.net
License: MIT
Download-URL: https://github.com/lambdalisue/histogramy/tarball/master
Keywords: 1-dimensional,analysis,histogram
Platform: UNKNOWN
Classifier: Intended Audience :: Developers
Classifier: License :: OSI Approved :: MIT License
Classifier: Programming Language :: Python
Classifier: Topic :: Internet :: WWW/HTTP
